{
  "fetched_at": "2026-04-27T13:08:56Z",
  "stories": {
    "crucible": {
      "id": "14526896",
      "title": "Crucible",
      "fandom": "Star Wars",
      "chapters": "19",
      "words": "101,207",
      "updated": "4/22",
      "favs": "256",
      "follows": "326"
    },
    "woe": {
      "id": "14533340",
      "title": "Woe to the Vanquished",
      "fandom": "ASOIAF",
      "chapters": "17",
      "words": "88,792",
      "updated": "4/21",
      "favs": "515",
      "follows": "641"
    },
    "shadow": {
      "id": "14455132",
      "title": "Shadow and Lightning",
      "fandom": "Harry Potter",
      "chapters": "22",
      "words": "104,074",
      "updated": "4/18",
      "favs": "466",
      "follows": "607"
    },
    "lightning": {
      "id": "14414477",
      "title": "Of Lightning and Blood",
      "fandom": "Skyrim",
      "chapters": "29",
      "words": "269,684",
      "updated": "17h",
      "favs": "618",
      "follows": "778"
    },
    "frost": {
      "id": "14436816",
      "title": "Frost and Death",
      "fandom": "Danny Phantom",
      "chapters": "8",
      "words": "50,241",
      "updated": "7/16/2025",
      "favs": "133",
      "follows": "176"
    }
  }
}